{
  "version": "5.1.1",
  "flags": {},
  "shapes": [
    {
      "label": "tarball",
      "points": [
        [
          356.08396946564886,
          407.6106870229008
        ],
        [
          383.94656488549623,
          434.3282442748092
        ]
      ],
      "group_id": null,
      "shape_type": "rectangle",
      "flags": {}
    },
    {
      "label": "tarball",
      "points": [
        [
          301.88549618320616,
          461.42748091603056
        ],
        [
          331.65648854961836,
          491.19847328244276
        ]
      ],
      "group_id": null,
      "shape_type": "rectangle",
      "flags": {}
    },
    {
      "label": "tarball",
      "points": [
        [
          278.22137404580155,
          547.6870229007634
        ],
        [
          306.46564885496184,
          574.4045801526718
        ]
      ],
      "group_id": null,
      "shape_type": "rectangle",
      "flags": {}
    },
    {
      "label": "tarball",
      "points": [
        [
          483.94656488549623,
          457.2290076335878
        ],
        [
          514.0992366412214,
          489.29007633587787
        ]
      ],
      "group_id": null,
      "shape_type": "rectangle",
      "flags": {}
    },
    {
      "label": "tarball",
      "points": [
        [
          558.3740458015268,
          553.0305343511451
        ],
        [
          582.4198473282443,
          578.6030534351145
        ]
      ],
      "group_id": null,
      "shape_type": "rectangle",
      "flags": {}
    },
    {
      "label": "tarball",
      "points": [
        [
          474.40458015267177,
          631.6564885496183
        ],
        [
          498.45038167938935,
          657.2290076335878
        ]
      ],
      "group_id": null,
      "shape_type": "rectangle",
      "flags": {}
    },
    {
      "label": "tarball",
      "points": [
        [
          435.47328244274814,
          593.4885496183206
        ],
        [
          461.80916030534354,
          620.969465648855
        ]
      ],
      "group_id": null,
      "shape_type": "rectangle",
      "flags": {}
    },
    {
      "label": "nbwl",
      "points": [
        [
          224.7450980392157,
          290.1045751633987
        ],
        [
          618.2091503267974,
          695.3333333333334
        ]
      ],
      "group_id": null,
      "shape_type": "rectangle",
      "flags": {}
    },
    {
      "label": "tarball",
      "points": [
        [
          35.863636363636374,
          44.95454545454548
        ],
        [
          85.2399403874814,
          0.0
        ]
      ],
      "group_id": null,
      "shape_type": "rectangle",
      "flags": {}
    },
    {
      "label": "tarball",
      "points": [
        [
          266.92424242424244,
          36.62121212121214
        ],
        [
          307.94000000000005,
          7.105427357601002e-15
        ]
      ],
      "group_id": null,
      "shape_type": "rectangle",
      "flags": {}
    }
  ],
  "imagePath": "00000073.png",
  "imageData": null,
  "imageHeight": 1024,
  "imageWidth": 1024
}