{
  "version": "5.1.1",
  "flags": {},
  "shapes": [
    {
      "label": "side",
      "points": [
        [
          41.349999999999994,
          26.45
        ],
        [
          95.45,
          68.55
        ],
        [
          71.85,
          113.64999999999999
        ],
        [
          42.95,
          92.14999999999999
        ],
        [
          47.45,
          64.55
        ]
      ],
      "group_id": null,
      "shape_type": "polygon",
      "flags": {}
    },
    {
      "label": "side",
      "points": [
        [
          42.849999999999994,
          91.95
        ],
        [
          46.64999999999999,
          110.85
        ],
        [
          71.85,
          114.14999999999999
        ]
      ],
      "group_id": null,
      "shape_type": "polygon",
      "flags": {}
    }
  ],
  "imagePath": "00000379.png",
  "imageData": null,
  "imageHeight": 128,
  "imageWidth": 128
}